deen/__init__.py
deen/constants.py
deen/exceptions.py
deen/loader.py
deen/logger.py
deen/main.py
deen/gui/__init__.py
deen/gui/core.py
deen/gui/encoder.py
deen/gui/widgets/__init__.py
deen/gui/widgets/formatted.py
deen/gui/widgets/hex.py
deen/gui/widgets/log.py
deen/gui/widgets/text.py
deen/gui/widgets/ui_deenencoderwidget.py
deen/gui/widgets/ui_deenfuzzysearch.py
deen/gui/widgets/ui_deenmainwindow.py
deen/gui/widgets/ui_deenpluginjwt.py
deen/gui/widgets/ui_deenpluginsyntaxhighlighter.py
deen/gui/widgets/ui_deenpluginx509clone.py
deen/media/document-save-as.svg
deen/media/edit-clear.svg
deen/media/edit-copy.svg
deen/media/go-up.svg
deen/media/icon.png
deen/media/view-formatted.svg
deen/media/view-hex.svg
deen/media/view-text.svg
deen/media/dark/document-save-as.svg
deen/media/dark/edit-clear.svg
deen/media/dark/edit-copy.svg
deen/media/dark/go-up.svg
deen/media/dark/view-formatted.svg
deen/media/dark/view-hex.svg
deen/media/dark/view-text.svg
deen/plugins/__init__.py
deen/plugins/assemblies/__base__.py
deen/plugins/assemblies/__init__.py
deen/plugins/assemblies/aarch64.py
deen/plugins/assemblies/arm.py
deen/plugins/assemblies/mips.py
deen/plugins/assemblies/sparc.py
deen/plugins/assemblies/x86.py
deen/plugins/codecs/__init__.py
deen/plugins/codecs/plugin_base64.py
deen/plugins/codecs/plugin_binhex4.py
deen/plugins/codecs/plugin_hex.py
deen/plugins/codecs/plugin_html.py
deen/plugins/codecs/plugin_jwt.py
deen/plugins/codecs/plugin_jwt_jose.py
deen/plugins/codecs/plugin_quopri.py
deen/plugins/codecs/plugin_rot13.py
deen/plugins/codecs/plugin_timestamps.py
deen/plugins/codecs/plugin_url.py
deen/plugins/codecs/plugin_uu.py
deen/plugins/compressions/__init__.py
deen/plugins/compressions/plugin_bzip2.py
deen/plugins/compressions/plugin_deflate.py
deen/plugins/compressions/plugin_gzip.py
deen/plugins/formatters/__init__.py
deen/plugins/formatters/plugin_highlight.py
deen/plugins/formatters/plugin_html.py
deen/plugins/formatters/plugin_jsbeautifier.py
deen-2.0.1.dist-info/LICENSE
deen-2.0.1.dist-info/METADATA
deen-2.0.1.dist-info/WHEEL
deen-2.0.1.dist-info/entry_points.txt
deen-2.0.1.dist-info/top_level.txt
deen-2.0.1.dist-info/RECORD
