Metadata-Version: 2.1
Name: deen
Version: 2.0.1
Summary: Generic data DEcoding/ENcoding application built with PyQt5
Home-page: https://github.com/takeshixx/deen
Author: takeshix
License: Apache 2.0
Platform: UNKNOWN
Classifier: Programming Language :: Python :: 3
Classifier: License :: OSI Approved :: Apache Software License
Classifier: Operating System :: OS Independent
Requires-Dist: PyQt5
Requires-Dist: jsbeautifier
Requires-Dist: dicttoxml
Requires-Dist: xmltodict
Requires-Dist: bcrypt
Requires-Dist: python-jose
Requires-Dist: pyOpenSSL
Provides-Extra: assembling
Requires-Dist: keystone-engine ; extra == 'assembling'
Provides-Extra: disassembling
Requires-Dist: capstone ; extra == 'disassembling'
